clipy/__init__.py
clipy/cli.py
clipy/cli_types.py
clipy/clipy.py
clipy/decorators.py
clipy/deprecated.py
clipyx-0.2.1.dist-info/licenses/LICENSE
clipyx-0.2.1.dist-info/METADATA
clipyx-0.2.1.dist-info/WHEEL
clipyx-0.2.1.dist-info/top_level.txt
clipyx-0.2.1.dist-info/RECORD
