Metadata-Version: 2.4
Name: clipyx
Version: 0.2.1
Summary: A command line interface package.
Author-email: G-Lauz <gabriel.lauzier@usherbrooke.ca>
Project-URL: Homepage, https://github.com/G-Lauz/clipy
Project-URL: Issues, https://github.com/G-Lauz/clipy/issues
Classifier: Intended Audience :: Developers
Classifier: License :: OSI Approved :: MIT License
Classifier: Programming Language :: Python :: 3
Classifier: Operating System :: OS Independent
Requires-Python: >=3.9
License-File: LICENSE
Dynamic: license-file
